[
  {
    "id": "0b8cb9b6-4eb7-407c-8527-511b68a6419a",
    "data": [
      {
        "text": "thanks but no",
        "userDefined": false
      }
    ],
    "isTemplate": false,
    "count": 0,
    "updated": 1531859391
  },
  {
    "id": "4fcde473-3400-4a7a-892a-2f7d3259b6db",
    "data": [
      {
        "text": "no way",
        "userDefined": false
      }
    ],
    "isTemplate": false,
    "count": 0,
    "updated": 1531859391
  },
  {
    "id": "2cfe88d5-1893-4a63-8998-194c909f5f44",
    "data": [
      {
        "text": "no",
        "userDefined": false
      }
    ],
    "isTemplate": false,
    "count": 2,
    "updated": 1531859391
  },
  {
    "id": "79bc7565-f1e3-498b-9ca3-ae78e78eff61",
    "data": [
      {
        "text": "no no don\u0027t",
        "userDefined": false
      }
    ],
    "isTemplate": false,
    "count": 0,
    "updated": 1531859391
  },
  {
    "id": "e468f9c2-448e-43c2-9215-0fc02bf87d9b",
    "data": [
      {
        "text": "na",
        "userDefined": false
      }
    ],
    "isTemplate": false,
    "count": 0,
    "updated": 1531859391
  },
  {
    "id": "635db42d-96e7-4167-b451-c0bfe83f6ec2",
    "data": [
      {
        "text": "no it isn\u0027t",
        "userDefined": false
      }
    ],
    "isTemplate": false,
    "count": 1,
    "updated": 1531859391
  },
  {
    "id": "fe56ba2f-5623-4118-9bd9-04374134f4a3",
    "data": [
      {
        "text": "don\u0027t",
        "userDefined": false
      }
    ],
    "isTemplate": false,
    "count": 0,
    "updated": 1531859391
  },
  {
    "id": "22a2db27-b335-4d85-a3f2-673247c23185",
    "data": [
      {
        "text": "nah I\u0027m good",
        "userDefined": false
      }
    ],
    "isTemplate": false,
    "count": 1,
    "updated": 1531859391
  },
  {
    "id": "b20c3c0f-18c5-45e8-9345-1b9c55a9145c",
    "data": [
      {
        "text": "no I cannot",
        "userDefined": false
      }
    ],
    "isTemplate": false,
    "count": 1,
    "updated": 1531859391
  },
  {
    "id": "a81905e3-d64d-4a0f-b2ca-6ffdff521fc2",
    "data": [
      {
        "text": "I can\u0027t",
        "userDefined": false
      }
    ],
    "isTemplate": false,
    "count": 0,
    "updated": 1531859391
  },
  {
    "id": "7f5d260f-2e21-4856-b215-00a4590cc1f8",
    "data": [
      {
        "text": "nothing",
        "userDefined": false
      }
    ],
    "isTemplate": false,
    "count": 0,
    "updated": 1531859391
  },
  {
    "id": "619a64d0-2882-4944-8877-3284c969c592",
    "data": [
      {
        "text": "no that\u0027s okay",
        "userDefined": false
      }
    ],
    "isTemplate": false,
    "count": 0,
    "updated": 1531859391
  },
  {
    "id": "bfd94e17-8049-481e-8f71-559635e0b7dc",
    "data": [
      {
        "text": "no not really",
        "userDefined": false
      }
    ],
    "isTemplate": false,
    "count": 0,
    "updated": 1531859391
  },
  {
    "id": "ec7f1ca0-5fdd-4f59-a958-3fa67074b81b",
    "data": [
      {
        "text": "nope not really",
        "userDefined": false
      }
    ],
    "isTemplate": false,
    "count": 0,
    "updated": 1531859391
  },
  {
    "id": "56b42f6b-cd47-437e-96bb-c1f70a8950ad",
    "data": [
      {
        "text": "nope",
        "userDefined": false
      }
    ],
    "isTemplate": false,
    "count": 1,
    "updated": 1531859391
  },
  {
    "id": "3c71d50a-6b05-4f35-8e0b-d6004ee53c48",
    "data": [
      {
        "text": "thanks but not this time",
        "userDefined": false
      }
    ],
    "isTemplate": false,
    "count": 1,
    "updated": 1531859391
  },
  {
    "id": "17adb62e-244e-4c6d-a6ed-f703b067c9ba",
    "data": [
      {
        "text": "I don\u0027t think so",
        "userDefined": false
      }
    ],
    "isTemplate": false,
    "count": 1,
    "updated": 1531859391
  },
  {
    "id": "8c3b0b78-9cd1-43aa-bbf9-0d6114b9c735",
    "data": [
      {
        "text": "I disagree",
        "userDefined": false
      }
    ],
    "isTemplate": false,
    "count": 2,
    "updated": 1531859391
  },
  {
    "id": "0fa60e8e-5903-4ca7-ac18-1ee6ebc20ef8",
    "data": [
      {
        "text": "no maybe next time",
        "userDefined": false
      }
    ],
    "isTemplate": false,
    "count": 0,
    "updated": 1531859391
  },
  {
    "id": "10d6fd8c-8b29-4d67-b98d-013370bf0574",
    "data": [
      {
        "text": "not this time",
        "userDefined": false
      }
    ],
    "isTemplate": false,
    "count": 0,
    "updated": 1531859391
  },
  {
    "id": "04ea6185-ec2e-4d72-b1b0-a997d0cdece1",
    "data": [
      {
        "text": "no don\u0027t",
        "userDefined": false
      }
    ],
    "isTemplate": false,
    "count": 0,
    "updated": 1531859391
  },
  {
    "id": "f11d1248-dd09-46bb-bebd-3fbf2a8bc165",
    "data": [
      {
        "text": "no we are good",
        "userDefined": false
      }
    ],
    "isTemplate": false,
    "count": 0,
    "updated": 1531859391
  },
  {
    "id": "0a3a2300-2d8e-4379-85f1-5c1c7cc96399",
    "data": [
      {
        "text": "don\u0027t do it",
        "userDefined": false
      }
    ],
    "isTemplate": false,
    "count": 3,
    "updated": 1531859391
  },
  {
    "id": "aa31f8dc-f19c-43e1-83a9-f173088dc2a9",
    "data": [
      {
        "text": "no that\u0027s be all",
        "userDefined": false
      }
    ],
    "isTemplate": false,
    "count": 0,
    "updated": 1531859391
  },
  {
    "id": "59409c35-ee3e-4e8d-9fae-939dcbc32312",
    "data": [
      {
        "text": "not right now",
        "userDefined": false
      }
    ],
    "isTemplate": false,
    "count": 0,
    "updated": 1531859391
  },
  {
    "id": "5008d0f6-4461-45ba-b0f7-bbe1eef97854",
    "data": [
      {
        "text": "nothing else thanks",
        "userDefined": false
      }
    ],
    "isTemplate": false,
    "count": 0,
    "updated": 1531859391
  },
  {
    "id": "36c63616-6365-4c41-8ed9-d5004a8915c8",
    "data": [
      {
        "text": "no thanks",
        "userDefined": false
      }
    ],
    "isTemplate": false,
    "count": 0,
    "updated": 1531859391
  },
  {
    "id": "d8cfa8cc-c839-4053-bd4e-2d5bc68a6b6a",
    "data": [
      {
        "text": "no that\u0027s ok",
        "userDefined": false
      }
    ],
    "isTemplate": false,
    "count": 1,
    "updated": 1531859391
  },
  {
    "id": "7f1da32f-c50e-4117-ad56-8b715b646e9a",
    "data": [
      {
        "text": "I don\u0027t want that",
        "userDefined": false
      }
    ],
    "isTemplate": false,
    "count": 0,
    "updated": 1531859391
  },
  {
    "id": "d0bbdddd-5371-4ab8-a47b-9e5c9111436d",
    "data": [
      {
        "text": "definitely not",
        "userDefined": false
      }
    ],
    "isTemplate": false,
    "count": 3,
    "updated": 1531859391
  },
  {
    "id": "c06d0a4c-4b29-48b0-83df-81d453af02f6",
    "data": [
      {
        "text": "nothing else",
        "userDefined": false
      }
    ],
    "isTemplate": false,
    "count": 1,
    "updated": 1531859391
  },
  {
    "id": "2393bd3f-2ab3-41b0-b5e3-08bba90a9f40",
    "data": [
      {
        "text": "not",
        "userDefined": false
      }
    ],
    "isTemplate": false,
    "count": 0,
    "updated": 1531859391
  },
  {
    "id": "5c1a1c95-6a81-4f37-9d16-02c9637ae980",
    "data": [
      {
        "text": "not at all",
        "userDefined": false
      }
    ],
    "isTemplate": false,
    "count": 0,
    "updated": 1531859391
  },
  {
    "id": "ae22940a-467d-4fab-8ab8-7862ed8f6cb5",
    "data": [
      {
        "text": "no never",
        "userDefined": false
      }
    ],
    "isTemplate": false,
    "count": 0,
    "updated": 1531859391
  },
  {
    "id": "b294ab6a-acca-4963-9a79-0e5659c98e99",
    "data": [
      {
        "text": "never",
        "userDefined": false
      }
    ],
    "isTemplate": false,
    "count": 0,
    "updated": 1531859391
  },
  {
    "id": "a7996185-48b5-48a0-9332-faff6b5349c3",
    "data": [
      {
        "text": "no way no",
        "userDefined": false
      }
    ],
    "isTemplate": false,
    "count": 0,
    "updated": 1531859391
  },
  {
    "id": "5ad4655a-1a30-4796-affd-808cd4252455",
    "data": [
      {
        "text": "not really",
        "userDefined": false
      }
    ],
    "isTemplate": false,
    "count": 0,
    "updated": 1531859391
  },
  {
    "id": "b43e0c71-2160-441a-bced-19a952f54ded",
    "data": [
      {
        "text": "nah",
        "userDefined": false
      }
    ],
    "isTemplate": false,
    "count": 2,
    "updated": 1531859391
  },
  {
    "id": "eb136a12-0e59-43fd-9112-6c27e90ab660",
    "data": [
      {
        "text": "I don\u0027t",
        "userDefined": false
      }
    ],
    "isTemplate": false,
    "count": 0,
    "updated": 1531859391
  },
  {
    "id": "00ff20e3-421b-4ab7-960d-e00269e24d17",
    "data": [
      {
        "text": "I don\u0027t want",
        "userDefined": false
      }
    ],
    "isTemplate": false,
    "count": 0,
    "updated": 1531859391
  },
  {
    "id": "3ee34f9c-263a-4a73-97b5-a70881aebb26",
    "data": [
      {
        "text": "not ",
        "userDefined": false
      },
      {
        "text": "today",
        "meta": "@sys.ignore",
        "userDefined": false
      }
    ],
    "isTemplate": false,
    "count": 0,
    "updated": 1531859391
  },
  {
    "id": "647067fc-0c9c-4c67-9d14-1dac43c96077",
    "data": [
      {
        "text": "not interested",
        "userDefined": false
      }
    ],
    "isTemplate": false,
    "count": 0,
    "updated": 1531859391
  },
  {
    "id": "fd0c716e-f7c1-436d-95b0-b5f52ecc58ae",
    "data": [
      {
        "text": "no that\u0027s fine thank you",
        "userDefined": false
      }
    ],
    "isTemplate": false,
    "count": 0,
    "updated": 1531859391
  },
  {
    "id": "a7381d6e-a0e7-4bb1-880f-8a9ebe29ed69",
    "data": [
      {
        "text": "I\u0027m not",
        "userDefined": false
      }
    ],
    "isTemplate": false,
    "count": 3,
    "updated": 1531859391
  }
]